Workbook

Sheet JAN25
A1: Date | B1: Actual | C1: Budget | D1: Actual Cumm | E1: Budget Cumm | F1: FOOD | G1: Other
A2: 45658 | B2: ='JAN25'!$F2+'JAN25'!$G2 -> 130 | C2: 150 | D2: =B2 -> 130 | E2: =C2 -> 150 | F2: 110 | G2: 20 | I2: Gold | J2: 300
A3: 45659 | B3: ='JAN25'!$F3+'JAN25'!$G3 -> 80 | C3: 150 | D3: =D2+B3 -> 210 | E3: =C3+C2 -> 300 | F3: 80 | I3: SIP | J3: 2000 | L3: AC Bal(1st Jan) | M3: 44780
A4: 45660 | B4: ='JAN25'!$F4+'JAN25'!$G4 -> 100 | C4: 150 | D4: =D3+B4 -> 310 | E4: =C4+E3 -> 450 | F4: 100 | I4: Rent | J4: 7000 | M4: =SUM(J2:J9) -> 18710 | R4: =J2+J3+J5+J6+J7+J9+J10 -> 9310
A5: 45661 | B5: ='JAN25'!$F5+'JAN25'!$G5 -> 78 | C5: 150 | D5: =D4+B5 -> 388 | E5: =E4+150 -> 600 | F5: =25+25 -> 50 | G5: 28 | I5: Expenses | J5: =D32 -> 2590
A6: 45662 | B6: ='JAN25'!$F6+'JAN25'!$G6 -> 182 | C6: 150 | D6: =D5+B6 -> 570 | E6: =E5+150 -> 750 | F6: 150 | G6: 32 | I6: Travel | J6: =1200+1500 -> 2700
A7: 45663 | B7: ='JAN25'!$F7+'JAN25'!$G7 -> 60 | C7: 150 | D7: =D6+B7 -> 630 | E7: =E6+150 -> 900 | F7: 60 | I7: Medical | J7: 500
A8: 45664 | B8: ='JAN25'!$F8+'JAN25'!$G8 -> 237 | C8: 150 | D8: =D7+B8 -> 867 | E8: =E7+150 -> 1050 | F8: =24+35 -> 59 | G8: 178 | I8: Stocks | J8: 3000
A9: 45665 | B9: ='JAN25'!$F9+'JAN25'!$G9 -> 40 | C9: 150 | D9: =D8+B9 -> 907 | E9: =E8+150 -> 1200 | F9: =20+20 -> 40 | I9: Recharge | J9: 620
A10: 45666 | B10: ='JAN25'!$F10+'JAN25'!$G10 -> 72 | C10: 150 | D10: =D9+B10 -> 979 | E10: =E9+150 -> 1350 | F10: =12+35+25 -> 72 | I10: GYM | J10: 600
A11: 45667 | B11: ='JAN25'!$F11+'JAN25'!$G11 -> 212 | C11: 150 | D11: =D10+B11 -> 1191 | E11: =E10+150 -> 1500 | F11: 200 | G11: 12 | I11: MF | J11: 500
A12: 45668 | B12: ='JAN25'!$F12+'JAN25'!$G12 -> 75 | C12: 150 | D12: =D11+B12 -> 1266 | E12: =E11+150 -> 1650 | G12: 75
A13: 45669 | B13: ='JAN25'!$F13+'JAN25'!$G13 -> 0 | C13: 150 | D13: =D12+B13 -> 1266 | E13: =E12+150 -> 1800
A14: 45670 | B14: ='JAN25'!$F14+'JAN25'!$G14 -> 33 | C14: 150 | D14: =D13+B14 -> 1299 | E14: =E13+150 -> 1950 | G14: 33
A15: 45671 | B15: ='JAN25'!$F15+'JAN25'!$G15 -> 0 | C15: 150 | D15: =D14+B15 -> 1299 | E15: =E14+150 -> 2100
A16: 45672 | B16: ='JAN25'!$F16+'JAN25'!$G16 -> 33 | C16: 150 | D16: =D15+B16 -> 1332 | E16: =E15+150 -> 2250 | G16: 33
A17: 45673 | B17: ='JAN25'!$F17+'JAN25'!$G17 -> 71 | C17: 150 | D17: =D16+B17 -> 1403 | E17: =E16+150 -> 2400 | G17: 71
A18: 45674 | B18: ='JAN25'!$F18+'JAN25'!$G18 -> 12 | C18: 150 | D18: =D17+B18 -> 1415 | E18: =E17+150 -> 2550 | F18: 12
A19: 45675 | B19: ='JAN25'!$F19+'JAN25'!$G19 -> 178 | C19: 150 | D19: =D18+B19 -> 1593 | E19: =E18+150 -> 2700 | F19: 150 | G19: 28
A20: 45676 | B20: ='JAN25'!$F20+'JAN25'!$G20 -> 45 | C20: 150 | D20: =D19+B20 -> 1638 | E20: =E19+150 -> 2850 | F20: 45
A21: 45677 | B21: ='JAN25'!$F21+'JAN25'!$G21 -> 110 | C21: 150 | D21: =D20+B21 -> 1748 | E21: =E20+150 -> 3000 | F21: 60 | G21: 50
A22: 45678 | B22: ='JAN25'!$F22+'JAN25'!$G22 -> 45 | C22: 150 | D22: =D21+B22 -> 1793 | E22: =E21+150 -> 3150 | F22: 45
A23: 45679 | B23: ='JAN25'!$F23+'JAN25'!$G23 -> 32 | C23: 150 | D23: =D22+B23 -> 1825 | E23: =E22+150 -> 3300 | F23: =12+20 -> 32
A24: 45680 | B24: ='JAN25'!$F24+'JAN25'!$G24 -> 0 | C24: 150 | D24: =D23+B24 -> 1825 | E24: =E23+150 -> 3450 | F24: 0
A25: 45681 | B25: ='JAN25'!$F25+'JAN25'!$G25 -> 152 | C25: 150 | D25: =D24+B25 -> 1977 | E25: =E24+150 -> 3600 | F25: 12 | G25: 140
A26: 45682 | B26: ='JAN25'!$F26+'JAN25'!$G26 -> 69 | C26: 150 | D26: =D25+B26 -> 2046 | E26: =E25+150 -> 3750 | F26: =57+12 -> 69 | S26: =Q26*R26 -> 0
A27: 45683 | B27: ='JAN25'!$F27+'JAN25'!$G27 -> 160 | C27: 150 | D27: =D26+B27 -> 2206 | E27: =E26+150 -> 3900 | F27: 40 | G27: =120 -> 120
A28: 45684 | B28: ='JAN25'!$F28+'JAN25'!$G28 -> 32 | C28: 150 | D28: =D27+B28 -> 2238 | E28: =E27+150 -> 4050 | F28: =20+12 -> 32 | S28: =S27+U27 -> 0
A29: 45685 | B29: ='JAN25'!$F29+'JAN25'!$G29 -> 80 | C29: 150 | D29: =D28+B29 -> 2318 | E29: =E28+150 -> 4200 | F29: =80 -> 80
A30: 45686 | B30: ='JAN25'!$F30+'JAN25'!$G30 -> 20 | C30: 150 | D30: =D29+B30 -> 2338 | E30: =E29+150 -> 4350 | F30: 20
A31: 45687 | B31: ='JAN25'!$F31+'JAN25'!$G31 -> 90 | C31: 150 | D31: =D30+B31 -> 2428 | E31: =E30+150 -> 4500 | F31: 90
A32: 45688 | B32: ='JAN25'!$F32+'JAN25'!$G32 -> 162 | C32: 150 | D32: =D31+B32 -> 2590 | E32: =E31+150 -> 4650 | F32: =12+100+50 -> 162
A33: 45689 | B33: ='JAN25'!$F33+'JAN25'!$G33 -> 48 | C33: 150 | D33: ='JAN25'!$B33 -> 48 | E33: ='JAN25'!$C33 -> 150 | F33: 48 | I33: Gold | J33: 300 | L33: AC Bal(1st Feb) | M33: 44397
A34: 45690 | B34: ='JAN25'!$F34+'JAN25'!$G34 -> 114 | C34: 150 | D34: ='JAN25'!$B34+D33 -> 162 | E34: =E33+'JAN25'!$C34 -> 300 | F34: =65 -> 65 | G34: =23+26 -> 49 | I34: SIP | J34: 2000 | M34: =SUM(J33:J39) -> 13937
A35: 45691 | B35: ='JAN25'!$F35+'JAN25'!$G35 -> 55 | C35: 150 | D35: ='JAN25'!$B35+D34 -> 217 | E35: =E34+'JAN25'!$C35 -> 450 | F35: 55 | I35: ETF | J35: 500
A36: 45692 | B36: ='JAN25'!$F36+'JAN25'!$G36 -> 162 | C36: 150 | D36: ='JAN25'!$B36+D35 -> 379 | E36: =E35+'JAN25'!$C36 -> 600 | F36: =140+22 -> 162 | I36: Expenses | J36: =D60 -> 2737 | M36: =10000 -> 10000
A37: 45693 | B37: ='JAN25'!$F37+'JAN25'!$G37 -> 184 | C37: 150 | D37: ='JAN25'!$B37+D36 -> 563 | E37: =E36+'JAN25'!$C37 -> 750 | F37: =160+24 -> 184 | I37: GYM | J37: 600
A38: 45694 | B38: ='JAN25'!$F38+'JAN25'!$G38 -> 118 | C38: 150 | D38: ='JAN25'!$B38+D37 -> 681 | E38: =E37+'JAN25'!$C38 -> 900 | F38: =50+10+25+33 -> 118 | I38: Rent | J38: 7000
A39: 45695 | B39: ='JAN25'!$F39+'JAN25'!$G39 -> 12 | C39: 150 | D39: ='JAN25'!$B39+D38 -> 693 | E39: =E38+'JAN25'!$C39 -> 1050 | F39: 12 | I39: Airpods | J39: 800
A40: 45696 | B40: ='JAN25'!$F40+'JAN25'!$G40 -> 49 | C40: 150 | D40: ='JAN25'!$B40+D39 -> 742 | E40: =E39+'JAN25'!$C40 -> 1200 | F40: =14+10+25 -> 49 | I40: MF | J40: 500
A41: 45697 | B41: ='JAN25'!$F41+'JAN25'!$G41 -> 310 | C41: 150 | D41: ='JAN25'!$B41+D40 -> 1052 | E41: =E40+'JAN25'!$C41 -> 1350 | F41: 170 | G41: 140
A42: 45698 | B42: ='JAN25'!$F42+'JAN25'!$G42 -> 50 | C42: 150 | D42: ='JAN25'!$B42+D41 -> 1102 | E42: =E41+'JAN25'!$C42 -> 1500 | F42: =20+10+20 -> 50
A43: 45699 | B43: ='JAN25'!$F43+'JAN25'!$G43 -> 80 | C43: 150 | D43: ='JAN25'!$B43+D42 -> 1182 | E43: =E42+'JAN25'!$C43 -> 1650 | F43: 80
A44: 45700 | B44: ='JAN25'!$F44+'JAN25'!$G44 -> 75 | C44: 150 | D44: ='JAN25'!$B44+D43 -> 1257 | E44: =E43+'JAN25'!$C44 -> 1800 | F44: =25+20+30 -> 75
A45: 45701 | B45: ='JAN25'!$F45+'JAN25'!$G45 -> 75 | C45: 150 | D45: ='JAN25'!$B45+D44 -> 1332 | E45: =E44+'JAN25'!$C45 -> 1950 | F45: =60+15 -> 75
A46: 45702 | B46: ='JAN25'!$F46+'JAN25'!$G46 -> 57 | C46: 150 | D46: ='JAN25'!$B46+D45 -> 1389 | E46: =E45+'JAN25'!$C46 -> 2100 | F46: =27+20+10 -> 57
A47: 45703 | B47: ='JAN25'!$F47+'JAN25'!$G47 -> 100 | C47: 150 | D47: ='JAN25'!$B47+D46 -> 1489 | E47: =E46+'JAN25'!$C47 -> 2250 | F47: 100
A48: 45704 | B48: ='JAN25'!$F48+'JAN25'!$G48 -> 51 | C48: 150 | D48: ='JAN25'!$B48+D47 -> 1540 | E48: =E47+'JAN25'!$C48 -> 2400 | F48: =36+15 -> 51
A49: 45705 | B49: ='JAN25'!$F49+'JAN25'!$G49 -> 0 | C49: 150 | D49: ='JAN25'!$B49+D48 -> 1540 | E49: =E48+'JAN25'!$C49 -> 2550
A50: 45706 | B50: ='JAN25'!$F50+'JAN25'!$G50 -> 50 | C50: 150 | D50: ='JAN25'!$B50+D49 -> 1590 | E50: =E49+'JAN25'!$C50 -> 2700 | F50: =50 -> 50
A51: 45707 | B51: ='JAN25'!$F51+'JAN25'!$G51 -> 0 | C51: 150 | D51: ='JAN25'!$B51+D50 -> 1590 | E51: =E50+'JAN25'!$C51 -> 2850
A52: 45708 | B52: ='JAN25'!$F52+'JAN25'!$G52 -> 60 | C52: 150 | D52: ='JAN25'!$B52+D51 -> 1650 | E52: =E51+'JAN25'!$C52 -> 3000 | F52: 60
A53: 45709 | B53: ='JAN25'!$F53+'JAN25'!$G53 -> 10 | C53: 150 | D53: ='JAN25'!$B53+D52 -> 1660 | E53: =E52+'JAN25'!$C53 -> 3150 | F53: 10
A54: 45710 | B54: ='JAN25'!$F54+'JAN25'!$G54 -> 225 | C54: 150 | D54: ='JAN25'!$B54+D53 -> 1885 | E54: =E53+'JAN25'!$C54 -> 3300 | F54: =80+40+20+65+20 -> 225
A55: 45711 | B55: ='JAN25'!$F55+'JAN25'!$G55 -> 360 | C55: 150 | D55: ='JAN25'!$B55+D54 -> 2245 | E55: =E54+'JAN25'!$C55 -> 3450 | F55: 160 | G55: 200
A56: 45712 | B56: ='JAN25'!$F56+'JAN25'!$G56 -> 40 | C56: 150 | D56: ='JAN25'!$B56+D55 -> 2285 | E56: =E55+'JAN25'!$C56 -> 3600 | F56: =15+25 -> 40
A57: 45713 | B57: ='JAN25'!$F57+'JAN25'!$G57 -> 100 | C57: 150 | D57: ='JAN25'!$B57+D56 -> 2385 | E57: =E56+'JAN25'!$C57 -> 3750 | F57: 100
A58: 45714 | B58: ='JAN25'!$F58+'JAN25'!$G58 -> 180 | C58: 150 | D58: ='JAN25'!$B58+D57 -> 2565 | E58: =E57+'JAN25'!$C58 -> 3900 | F58: =20 -> 20 | G58: 160
A59: 45715 | B59: ='JAN25'!$F59+'JAN25'!$G59 -> 75 | C59: 150 | D59: ='JAN25'!$B59+D58 -> 2640 | E59: =E58+'JAN25'!$C59 -> 4050 | F59: =50+25 -> 75
A60: 45716 | B60: ='JAN25'!$F60+'JAN25'!$G60 -> 97 | C60: 150 | D60: ='JAN25'!$B60+D59 -> 2737 | E60: =E59+'JAN25'!$C60 -> 4200 | F60: =60+37 -> 97
A61: 45717 | B61: ='JAN25'!$F61+'JAN25'!$G61 -> 337 | C61: 150 | D61: ='JAN25'!$B61 -> 337 | E61: 150 | F61: =37+30 -> 67 | G61: =60+60+150 -> 270 | I61: Gold | J61: 300 | L61: AC Bal(1st Mar) | M61: 57397
A62: 45718 | B62: ='JAN25'!$F62+'JAN25'!$G62 -> 65 | C62: 150 | D62: =D61+'JAN25'!$B62 -> 402 | E62: =E61+'JAN25'!$C62 -> 300 | F62: =50+15 -> 65 | I62: SIP | J62: 2000
A63: 45719 | B63: ='JAN25'!$F63+'JAN25'!$G63 -> 35 | C63: 150 | D63: =D62+'JAN25'!$B63 -> 437 | E63: =E62+'JAN25'!$C63 -> 450 | F63: =35 -> 35 | I63: ETF | J63: 500
A64: 45720 | B64: ='JAN25'!$F64+'JAN25'!$G64 -> 127 | C64: 150 | D64: =D63+'JAN25'!$B64 -> 564 | E64: =E63+'JAN25'!$C64 -> 600 | F64: 25 | G64: =45+57 -> 102 | I64: Expenses | J64: =D91 -> 2619
A65: 45721 | B65: ='JAN25'!$F65+'JAN25'!$G65 -> 45 | C65: 150 | D65: =D64+'JAN25'!$B65 -> 609 | E65: =E64+'JAN25'!$C65 -> 750 | F65: =20+25 -> 45 | I65: Skincare | J65: 630
A66: 45722 | B66: ='JAN25'!$F66+'JAN25'!$G66 -> 60 | C66: 150 | D66: =D65+'JAN25'!$B66 -> 669 | E66: =E65+'JAN25'!$C66 -> 900 | F66: 60 | I66: Rent | J66: 7000
A67: 45723 | B67: ='JAN25'!$F67+'JAN25'!$G67 -> 220 | C67: 150 | D67: =D66+'JAN25'!$B67 -> 889 | E67: =E66+'JAN25'!$C67 -> 1050 | F67: 220 | I67: Recharge | J67: 580
A68: 45724 | B68: ='JAN25'!$F68+'JAN25'!$G68 -> 130 | C68: 150 | D68: =D67+'JAN25'!$B68 -> 1019 | E68: =E67+'JAN25'!$C68 -> 1200 | F68: =60+70 -> 130 | I68: Stocks | J68: 3000
A69: 45725 | B69: ='JAN25'!$F69+'JAN25'!$G69 -> 383 | C69: 150 | D69: =D68+'JAN25'!$B69 -> 1402 | E69: =E68+'JAN25'!$C69 -> 1350 | F69: =20+100+100+65 -> 285 | G69: =60+38 -> 98 | I69: Shopping | J69: 1347
A70: 45726 | B70: ='JAN25'!$F70+'JAN25'!$G70 -> 20 | C70: 150 | D70: =D69+'JAN25'!$B70 -> 1422 | E70: =E69+'JAN25'!$C70 -> 1500 | F70: 20 | I70: Specs | J70: 3350
A71: 45727 | B71: ='JAN25'!$F71+'JAN25'!$G71 -> 68 | C71: 150 | D71: =D70+'JAN25'!$B71 -> 1490 | E71: =E70+'JAN25'!$C71 -> 1650 | G71: =40+28 -> 68 | I71: Travel | J71: 3000
A72: 45728 | B72: ='JAN25'!$F72+'JAN25'!$G72 -> 50 | C72: 150 | D72: =D71+'JAN25'!$B72 -> 1540 | E72: =E71+'JAN25'!$C72 -> 1800 | G72: =30+20 -> 50 | I72: MF | J72: 500
A73: 45729 | B73: ='JAN25'!$F73+'JAN25'!$G73 -> 40 | C73: 150 | D73: =D72+'JAN25'!$B73 -> 1580 | E73: =E72+'JAN25'!$C73 -> 1950 | F73: 40
A74: 45730 | B74: ='JAN25'!$F74+'JAN25'!$G74 -> 35 | C74: 150 | D74: =D73+'JAN25'!$B74 -> 1615 | E74: =E73+'JAN25'!$C74 -> 2100 | F74: =25+10 -> 35
A75: 45731 | B75: ='JAN25'!$F75+'JAN25'!$G75 -> 37 | C75: 150 | D75: =D74+'JAN25'!$B75 -> 1652 | E75: =E74+'JAN25'!$C75 -> 2250 | F75: =37 -> 37
A76: 45732 | B76: ='JAN25'!$F76+'JAN25'!$G76 -> 163 | C76: 150 | D76: =D75+'JAN25'!$B76 -> 1815 | E76: =E75+'JAN25'!$C76 -> 2400 | F76: =25+60 -> 85 | G76: =30+48 -> 78
A77: 45733 | B77: ='JAN25'!$F77+'JAN25'!$G77 -> 20 | C77: 150 | D77: =D76+'JAN25'!$B77 -> 1835 | E77: =E76+'JAN25'!$C77 -> 2550 | F77: 20
A78: 45734 | B78: ='JAN25'!$F78+'JAN25'!$G78 -> 10 | C78: 150 | D78: =D77+'JAN25'!$B78 -> 1845 | E78: =E77+'JAN25'!$C78 -> 2700 | F78: 10
A79: 45735 | B79: ='JAN25'!$F79+'JAN25'!$G79 -> 90 | C79: 150 | D79: =D78+'JAN25'!$B79 -> 1935 | E79: =E78+'JAN25'!$C79 -> 2850 | F79: =70+20 -> 90
A80: 45736 | B80: ='JAN25'!$F80+'JAN25'!$G80 -> 40 | C80: 150 | D80: =D79+'JAN25'!$B80 -> 1975 | E80: =E79+'JAN25'!$C80 -> 3000 | F80: 40
A81: 45737 | B81: ='JAN25'!$F81+'JAN25'!$G81 -> 30 | C81: 150 | D81: =D80+'JAN25'!$B81 -> 2005 | E81: =E80+'JAN25'!$C81 -> 3150 | F81: 30
A82: 45738 | B82: ='JAN25'!$F82+'JAN25'!$G82 -> 70 | C82: 150 | D82: =D81+'JAN25'!$B82 -> 2075 | E82: =E81+'JAN25'!$C82 -> 3300 | F82: =20+30+20 -> 70
A83: 45739 | B83: ='JAN25'!$F83+'JAN25'!$G83 -> 374 | C83: 150 | D83: =D82+'JAN25'!$B83 -> 2449 | E83: =E82+'JAN25'!$C83 -> 3450 | F83: =14+300+30 -> 344 | G83: 30
A84: 45740 | B84: ='JAN25'!$F84+'JAN25'!$G84 -> 20 | C84: 150 | D84: =D83+'JAN25'!$B84 -> 2469 | E84: =E83+'JAN25'!$C84 -> 3600 | F84: 20
A85: 45741 | B85: ='JAN25'!$F85+'JAN25'!$G85 -> 90 | C85: 150 | D85: =D84+'JAN25'!$B85 -> 2559 | E85: =E84+'JAN25'!$C85 -> 3750 | F85: =90 -> 90
A86: 45742 | B86: ='JAN25'!$F86+'JAN25'!$G86 -> 60 | C86: 150 | D86: =D85+'JAN25'!$B86 -> 2619 | E86: =E85+'JAN25'!$C86 -> 3900 | F86: 60
A87: 45743 | B87: ='JAN25'!$F87+'JAN25'!$G87 -> 0 | C87: 150 | D87: =D86+'JAN25'!$B87 -> 2619 | E87: =E86+'JAN25'!$C87 -> 4050
A88: 45744 | B88: ='JAN25'!$F88+'JAN25'!$G88 -> 0 | C88: 150 | D88: =D87+'JAN25'!$B88 -> 2619 | E88: =E87+'JAN25'!$C88 -> 4200
A89: 45745 | C89: 150 | D89: =D88+'JAN25'!$B89 -> 2619 | E89: =E88+'JAN25'!$C89 -> 4350
A90: 45746 | C90: 150 | D90: =D89+'JAN25'!$B90 -> 2619 | E90: =E89+'JAN25'!$C90 -> 4500
A91: 45747 | C91: 150 | D91: =D90+'JAN25'!$B91 -> 2619 | E91: =E90+'JAN25'!$C91 -> 4650
A92: 45748 | B92: ='JAN25'!$F92+'JAN25'!$G92 -> 0 | C92: 150 | D92: ='JAN25'!$B92 -> 0 | E92: ='JAN25'!$C92 -> 150 | I92: Gold | J92: 300 | L92: AC Bal(1st arpril) | M92: 63000
A93: 45749 | B93: ='JAN25'!$F93+'JAN25'!$G93 -> 0 | C93: 150 | D93: ='JAN25'!$B93+D92 -> 0 | E93: ='JAN25'!$C93+E92 -> 300 | I93: SIP | J93: 2000
A94: 45750 | B94: ='JAN25'!$F94+'JAN25'!$G94 -> 0 | C94: 150 | D94: ='JAN25'!$B94+D93 -> 0 | E94: ='JAN25'!$C94+E93 -> 450 | I94: ETF | J94: 500
A95: 45751 | B95: ='JAN25'!$F95+'JAN25'!$G95 -> 0 | C95: 150 | D95: ='JAN25'!$B95+D94 -> 0 | E95: ='JAN25'!$C95+E94 -> 600 | I95: Expenses | J95: =D121 -> 1614
A96: 45752 | B96: ='JAN25'!$F96+'JAN25'!$G96 -> 0 | C96: 150 | D96: ='JAN25'!$B96+D95 -> 0 | E96: ='JAN25'!$C96+E95 -> 750 | I96: Trip | J96: 2600
A97: 45753 | B97: ='JAN25'!$F97+'JAN25'!$G97 -> 0 | C97: 150 | D97: ='JAN25'!$B97+D96 -> 0 | E97: ='JAN25'!$C97+E96 -> 900 | I97: Rent | J97: 7000
A98: 45754 | B98: ='JAN25'!$F98+'JAN25'!$G98 -> 30 | C98: 150 | D98: ='JAN25'!$B98+D97 -> 30 | E98: ='JAN25'!$C98+E97 -> 1050 | F98: 30 | I98: Shopping | J98: =800+1480+600 -> 2880
A99: 45755 | B99: ='JAN25'!$F99+'JAN25'!$G99 -> 85 | C99: 150 | D99: ='JAN25'!$B99+D98 -> 115 | E99: ='JAN25'!$C99+E98 -> 1200 | F99: 65 | G99: 20 | I99: Stocks | J99: 2000
A100: 45756 | B100: ='JAN25'!$F100+'JAN25'!$G100 -> 40 | C100: 150 | D100: ='JAN25'!$B100+D99 -> 155 | E100: ='JAN25'!$C100+E99 -> 1350 | F100: 40 | I100: Groceries | J100: 140
...

Sheet Pivot Table 1

Sheet SQL30(learning with jelly)
A1: Day | B1: Topics
A2: 45839
A3: 45840
A4: 45841
A5: 45842
A6: 45843
A7: 45844
A8: 45845 | B8: create tables
A9: 45846 | B9: where,and,or,comparision(=,<>,!=,<=) | C9: in | D9: like(%),(_)
A10: 45847 | B10: order by
A11: 45848 | B11: update,delete,alter,drop
A12: 45849 | B12: aggregate functions | C12: sum,count,avg
A13: 45850 | B13: group by,having
A14: 45851 | B14: case study
A15: 45852 | B15: left,inner,right joins
A16: 45853 | B16: full outer,union all, union(remove duplicates),self | C16: join 3 or more tables
A17: 45854 | B17: CTES SUBQUERIES
A18: 45855 | B18: PRACTICE OF 14&15
A19: 45856 | B19: SET OPEARATORS | C19: UNION,UNIONALL,INTERSECT(INNER),EXCEPT(RETURN ROWS ONLY FROM FIRST TABLE that are not in 2 nd table)
A20: 45857 | B20: CTES
A21: 45858 | B21: practice ctes in website
A22: 45859 | B22: window functions | C22: over,partition by,row number
A23: 45860 | B23: Rank(skips the number) | C23: dense_rank(dont skip) | D23: lag
A24: 45861 | B24: String functions(length,upper,lower,substr,trim)
A25: 45862 | B25: practice(Windows,string functions)
A26: 45863 | B26: Case when statements
A27: 45864 | B27: Other functions(Coalesce,replace,date,strftime('%y-%m-%d),round(total,2) | C27: select firstname,lastname,replace(email,'@example.com','domain.com') from customers
A28: 45865 | B28: Mini project | C28: 1.what is average invoice total by customer.
B29: Mini project | C29: 2.what are the top 10 customers with most invoices.
B30: Mini project | C30: 3.what are top 10 customers by purchase amount
B31: Mini project | C31: 4.what are total sales by country
A32: 45866 | B32: Mini project-2 | C32: 1.use a cte and calculate total sales for year 2012. Include the month and total sales amount
C33: 2.calculate running total o sales for each customer include the customername,invoicedate,invoice total & running total (hind use window function)
C34: 3.Identify the highest spending customer in each country (include country,customername,total speding)
A35: 45867 | B35: Showcasing SQL work
A36: 45868 | B36: Final recap

Sheet Diet
A1: Date | B1: Breakfast | C1: Mid Morning snack | D1: Lunch | E1: Evening snacks | F1: Dinner | G1: Before Bed
A2: 45693 | B2: Eggs | C2: Nuts, froot smoothie | E2: Fruits, | G2: Milk,nuts
A3: 45694 | B3: to
A4: 45695
A5: 45696
A6: 45697
A7: 45698
A8: 45699
A9: 45700
A10: 45701
A11: 45702
A12: 45703
A13: 45704
A14: 45705
A17: To-do
A18: Mon | B18: Breakfast | D18: Lunch | F18: Snack | G18: Dinner

Sheet Consolidated_Exp
A1: Date | B1: Category | C1: Amount
A2: 45292 | B2: Rent | C2: 8000
A3: 45292 | B3: SIP | C3: 2000
A4: 45292 | B4: STOCKS | C4: 2000
A5: 45292 | B5: Travel | C5: 5000
A6: 45292 | B6: Expenses | C6: ='JAN 24'!D32 -> 4225
A7: 45323 | B7: Rent | C7: 8000
A8: 45323 | B8: SIP | C8: 2000
A9: 45323 | B9: Stocks | C9: 2000
A10: 45323 | B10: GOLD | C10: 300
A11: 45323 | B11: Hotstar | C11: 300
A12: 45323 | B12: Trust debt | C12: 150
A13: 45323 | B13: Shopping | C13: 500
A14: 45323 | B14: Expenses | C14: 3421
A15: 45352 | B15: Travel | C15: 1040
A16: 45352 | B16: Rent | C16: 8000
A17: 45352 | B17: SIP | C17: 2300
A18: 45352 | B18: Stocks | C18: 2000
... A40: 45413 | B40: Expenses | C40: 4650
A41: 45413 | B41: OTT | C41: =150 -> 150
A42: 45413 | B42: Total | C42: =SUM(C37:C41) -> 17100
A43: 45413 | B43: Salary | C43: 25000
A44: 45444 | B44: Stocks | C44: 2000
A45: 45444 | B45: SIP | C45: 2000
A46: 45444 | B46: Rent | C46: 8000
A47: 45444 | B47: Expenses | C47: 4237
A48: 45444 | B48: OTT | C48: 200
A49: 45444 | B49: GOLD | C49: 300
A50: 45658 | B50: GOLD | C50: 300
A51: 45658 | B51: SIP | C51: 2000
A52: 45658 | B52: Rent | C52: 7000
A53: 45658 | B53: Expenses | C53: 2590
A54: 45658 | B54: Travel | C54: =1200+1500 -> 2700
A55: 45658 | B55: Medical | C55: 500
A56: 45658 | B56: Stocks | C56: 3000
A57: 45658 | B57: Recharge | C57: 620
A58: 45658 | B58: GYM | C58: 600
A59: 45689 | B59: GOLD | C59: 300
A60: 45689 | B60: SIP | C60: 2000
A61: 45689 | B61: ETF | C61: 500
A62: 45689 | B62: Expenses | C62: 2737
A63: 45689 | B63: GYM | C63: 600
A64: 45689 | B64: Rent | C64: 7000
A65: 45689 | B65: Airpods | C65: 800
A66: 45689 | B66: MF | C66: 500
... A84: 45748 | B84: Rent | C84: 7000
A85: 45748 | B85: Shopping | C85: =800+1480+600 -> 2880
A86: 45748 | B86: Stocks | C86: 2000
A87: 45748 | B87: Groceries | C87: 140
A88: 45748 | B88: Bar nd kitchen | C88: 2400
A89: 45748 | B89: MF | C89: 500
A90: 45778 | B90: GOLD | C90: 800
A91: 45778 | B91: SIP | C91: 2000
A92: 45778 | B92: ETF | C92: 500
A93: 45778 | B93: Expenses | C93: 2697
A94: 45778 | B94: Movie | C94: 400
A95: 45778 | B95: Rent | C95: 7000
A96: 45778 | B96: Stocks | C96: 2000
A97: 45778 | B97: Party | C97: 1900
A98: 45778 | B98: Groceries | C98: =55+120 -> 175
A99: 45778 | B99: Recharge | C99: 580
A100: 45778 | B100: Hotstar | C100: 79
A101: 45778 | B101: credit card | C101: 600
A102: 45778 | B102: MF | C102: 500
A103: 45809 | B103: GOLD | C103: 800
A104: 45809 | B104: SIP | C104: 2500
A105: 45809 | B105: ETF | C105: 500
A106: 45809 | B106: Expenses | C106: 2570
A107: 45809 | B107: Stocks | C107: 2500
A108: 45809 | B108: Rent | C108: 7000
A109: 45809 | B109: Gift | C109: 600
A110: 45809 | B110: Groceries | C110: 570
... A118: 45839 | B118: Recharge | C118: 578
A119: 45839 | B119: Groceries | C119: =167+120+100 -> 387
A120: 45839 | B120: Shopping | C120: 350
A121: 45839 | B121: MF | C121: 500
A122: 45870 | B122: GOLD | C122: 1000
A123: 45870 | B123: SIP | C123: 2000
A124: 45870 | B124: ETF | C124: 500
A125: 45870 | B125: Expenses | C125: 2724
A126: 45870 | B126: Stocks | C126: 2000
A127: 45870 | B127: Rent | C127: 7000
A128: 45870 | B128: Movie | C128: 150
A129: 45870 | B129: Skincare | C129: 530
A130: 45870 | B130: Travel | C130: =1440+1550 -> 2990
A131: 45870 | B131: Movie | C131: 350
A132: 45870 | B132: MF | C132: 500
A133: 45901 | B133: GOLD | C133: 1000
A134: 45901 | B134: SIP | C134: 2000
A135: 45901 | B135: ETF | C135: 500
A136: 45901 | B136: Expenses | C136: 2025
A137: 45901 | B137: Stocks | C137: 0
A138: 45901 | B138: Rent | C138: 7000
A139: 45901 | B139: MF | C139: 2500
A140: 45901 | B140: Travel | C140: =1021+1083 -> 2104
A141: 45901 | B141: Medical | C141: 188
A142: 45901 | B142: Groceries | C142: 315
A143: 45901 | B143: Shopping | C143: =700 -> 700
A144: 45901 | B144: SIP | C144: =4000 -> 4000
A145: 45931 | B145: GOLD | C145: 1000
...

Sheet JAN 24
A1: Date | B1: Actual | C1: Budget | D1: Actual Cumm | E1: Budget Cumm
A2: 45292 | B2: =375+90 -> 465 | C2: 150 | D2: =B2 -> 465 | E2: =C2 -> 150
A3: 45293 | B3: 50 | C3: 150 | D3: =D2+B3 -> 515 | E3: =E2+150 -> 300
A4: 45294 | B4: 130 | C4: 150 | D4: =D3+B4 -> 645 | E4: =E3+150 -> 450
A5: 45295 | B5: 120 | C5: 150 | D5: =D4+B5 -> 765 | E5: =E4+150 -> 600
A6: 45296 | B6: 70 | C6: 150 | D6: =D5+B6 -> 835 | E6: =E5+150 -> 750
A7: 45297 | B7: 85 | C7: 150 | D7: =D6+B7 -> 920 | E7: =E6+150 -> 900
A8: 45298 | B8: =245+30+30+20 -> 325 | C8: 150 | D8: =D7+B8 -> 1245 | E8: =E7+150 -> 1050
A9: 45299 | B9: =250+30 -> 280 | C9: 150 | D9: =D8+B9 -> 1525 | E9: =E8+150 -> 1200
A10: 45300 | B10: 110 | C10: 150 | D10: =D9+B10 -> 1635 | E10: =E9+150 -> 1350
A11: 45301 | B11: 145 | C11: 150 | D11: =D10+B11 -> 1780 | E11: =E10+150 -> 1500
A12: 45302 | B12: 50 | C12: 150 | D12: =D11+B12 -> 1830 | E12: =E11+150 -> 1650
A13: 45303 | C13: 150 | D13: =D12+B13 -> 1830 | E13: =E12+150 -> 1800
A14: 45304 | C14: 150 | D14: =D13+B14 -> 1830 | E14: =E13+150 -> 1950
A15: 45305 | C15: 150 | D15: =D14+B15 -> 1830 | E15: =E14+150 -> 2100
A16: 45306 | C16: 150 | D16: =D15+B16 -> 1830 | E16: =E15+150 -> 2250
A17: 45307 | C17: 150 | D17: =D16+B17 -> 1830 | E17: =E16+150 -> 2400
A18: 45308 | B18: 110 | C18: 150 | D18: =D17+B18 -> 1940 | E18: =E17+150 -> 2550
A19: 45309 | B19: =85+40+15 -> 140 | C19: 150 | D19: =D18+B19 -> 2080 | E19: =E18+150 -> 2700
A20: 45310 | B20: 50 | C20: 150 | D20: =D19+B20 -> 2130 | E20: =E19+150 -> 2850
A21: 45311 | B21: =50+15 -> 65 | C21: 150 | D21: =D20+B21 -> 2195 | E21: =E20+150 -> 3000
A22: 45312 | B22: =115+40+15 -> 170 | C22: 150 | D22: =D21+B22 -> 2365 | E22: =E21+150 -> 3150
A23: 45313 | B23: 50 | C23: 150 | D23: =D22+B23 -> 2415 | E23: =E22+150 -> 3300
A24: 45314 | B24: 115 | C24: 150 | D24: =D23+B24 -> 2530 | E24: =E23+150 -> 3450
A25: 45315 | B25: 150 | C25: 150 | D25: =D24+B25 -> 2680 | E25: =E24+150 -> 3600
A26: 45316 | B26: 50 | C26: 150 | D26: =D25+B26 -> 2730 | E26: =E25+150 -> 3750
A27: 45317 | B27: =800+70+60+120 -> 1050 | C27: 150 | D27: =D26+B27 -> 3780 | E27: =E26+150 -> 3900
A28: 45318 | B28: 85 | C28: 150 | D28: =D27+B28 -> 3865 | E28: =E27+150 -> 4050
A29: 45319 | B29: 120 | C29: 150 | D29: =D28+B29 -> 3985 | E29: =E28+150 -> 4200
A30: 45320 | B30: 110 | C30: 150 | D30: =D29+B30 -> 4095 | E30: =E29+150 -> 4350
A31: 45321 | B31: 50 | C31: 150 | D31: =D30+B31 -> 4145 | E31: =E30+150 -> 4500
A32: 45322 | B32: 80 | C32: 150 | D32: =D31+B32 -> 4225 | E32: =E31+150 -> 4650
A33: 45323 | B33: 120 | C33: 150 | D33: 120 | E33: 150
A34: 45324 | B34: 50 | C34: 150 | D34: 170 | E34: 300
A35: 45325 | B35: 95 | C35: 150 | D35: 265 | E35: 450
A36: 45326 | B36: 270 | C36: 150 | D36: 535 | E36: 600
A37: 45327 | B37: 110 | C37: 150 | D37: 645 | E37: 750
A38: 45328 | B38: 100 | C38: 150 | D38: 745 | E38: 900
A39: 45329 | B39: 50 | C39: 150 | D39: 795 | E39: 1050
A40: 45330 | B40: 110 | C40: 150 | D40: 905 | E40: 1200
A41: 45331 | B41: 54 | C41: 150 | D41: 959 | E41: 1350
A42: 45332 | B42: 100 | C42: 150 | D42: 1059 | E42: 1500
A43: 45333 | B43: 90 | C43: 150 | D43: 1149 | E43: 1650
A44: 45334 | B44: 115 | C44: 150 | D44: 1264 | E44: 1800
... A60: 45350 | B60: 50 | C60: 150 | D60: 3421 | E60: 4200
A61: 45351 | C61: 150 | D61: 3421 | E61: 4350
A62: 45352 | C62: 150 | D62: 0 | E62: 150 | G62: Travel | H62: 1040
A63: 45353 | C63: 150 | D63: 0 | E63: 300 | G63: Rent | H63: 8000
A64: 45354 | C64: 150 | D64: 0 | E64: 450 | G64: SIPS | H64: 2300
A65: 45355 | C65: 150 | D65: 0 | E65: 600 | G65: Stocks | H65: 2000
A66: 45356 | C66: 150 | D66: 0 | E66: 750 | G66: Shopping | H66: 1000
A67: 45357 | B67: 120 | C67: 150 | D67: 120 | E67: 900 | G67: Health Care | H67: 500
A68: 45358 | B68: 170 | C68: 150 | D68: 290 | E68: 1050 | G68: Expenses | H68: 4035
A69: 45359 | B69: 195 | C69: 150 | D69: 485 | E69: 1200
A70: 45360 | B70: 80 | C70: 150 | D70: 565 | E70: 1350
A71: 45361 | B71: 135 | C71: 150 | D71: 700 | E71: 1500
A72: 45362 | B72: 85 | C72: 150 | D72: 785 | E72: 1650
A73: 45363 | B73: 95 | C73: 150 | D73: 880 | E73: 1800
A74: 45364 | B74: 105 | C74: 150 | D74: 985 | E74: 1950
A75: 45365 | B75: 75 | C75: 150 | D75: 1060 | E75: 2100
A76: 45366 | B76: 65 | C76: 150 | D76: 1125 | E76: 2250
A77: 45367 | B77: 100 | C77: 150 | D77: 1225 | E77: 2400
A78: 45368 | B78: 515 | C78: 150 | D78: 1740 | E78: 2550
A79: 45369 | B79: 110 | C79: 150 | D79: 1850 | E79: 2700
A80: 45370 | B80: 120 | C80: 150 | D80: 1970 | E80: 2850
... A92: 45382 | B92: 285 | C92: 150 | D92: 4035 | E92: 4650
A93: 45383 | B93: =40+60+10 -> 110 | C93: 150 | D93: =B93 -> 110 | E93: =C93 -> 150 | G93: Rent | H93: 8000
A94: 45384 | B94: =43+68+20 -> 131 | C94: 150 | D94: =D93+B94 -> 241 | E94: =E93+150 -> 300 | G94: SIP | H94: 2000
A95: 45385 | B95: =41+70+10+320 -> 441 | C95: 150 | D95: =D94+B95 -> 682 | E95: =E94+150 -> 450 | G95: Shopping | H95: 1700
A96: 45386 | C96: 150 | D96: =D95+B96 -> 682 | E96: =E95+150 -> 600 | G96: Travel | H96: 1500
A97: 45387 | C97: 150 | D97: =D96+B97 -> 682 | E97: =E96+150 -> 750 | G97: Stocks | H97: 3000
A98: 45388 | C98: 150 | D98: =D97+B98 -> 682 | E98: =E97+150 -> 900 | G98: Phone | H98: 750
A99: 45389 | C99: 150 | D99: =D98+B99 -> 682 | E99: =E98+150 -> 1050 | G99: Gold | H99: 300
A100: 45390 | C100: 150 | D100: =D99+B100 -> 682 | E100: =E99+150 -> 1200 | G100: Expenses | H100: ='JAN 24'!D122 -> 3137
A101: 45391 | C101: 150 | D101: =D100+B101 -> 682 | E101: =E100+150 -> 1350
A102: 45392 | C102: 150 | D102: =D101+B102 -> 682 | E102: =E101+150 -> 1500
A103: 45393 | B103: =60+35+60+10 -> 165 | C103: 150 | D103: =D102+B103 -> 847 | E103: =E102+150 -> 1650
A104: 45394 | B104: =35+50+40+10 -> 135 | C104: 150 | D104: =D103+B104 -> 982 | E104: =E103+150 -> 1800
A105: 45395 | B105: =40+35+80+20 -> 175 | C105: 150 | D105: =D104+B105 -> 1157 | E105: =E104+150 -> 1950
A106: 45396 | B106: =70+20+12+70 -> 172 | C106: 150 | D106: =D105+B106 -> 1329 | E106: =E105+150 -> 2100
A107: 45397 | B107: 110 | C107: 150 | D107: =D106+B107 -> 1439 | E107: =E106+150 -> 2250
A108: 45398 | B108: 75 | C108: 150 | D108: =D107+B108 -> 1514 | E108: =E107+150 -> 2400
A109: 45399 | B109: =85+40+10 -> 135 | C109: 150 | D109: =D108+B109 -> 1649 | E109: =E108+150 -> 2550
A110: 45400 | B110: =35+10+20 -> 65 | C110: 150 | D110: =D109+B110 -> 1714 | E110: =E109+150 -> 2700
A111: 45401 | B111: =50+40+10 -> 100 | C111: 150 | D111: =D110+B111 -> 1814 | E111: =E110+150 -> 2850
A112: 45402 | B112: 80 | C112: 150 | D112: =D111+B112 -> 1894 | E112: =E111+150 -> 3000
A113: 45403 | B113: =70+190+45 -> 305 | C113: 150 | D113: =D112+B113 -> 2199 | E113: =E112+150 -> 3150
A114: 45404 | B114: 80 | C114: 150 | D114: =D113+B114 -> 2279 | E114: =E113+150 -> 3300
A115: 45405 | B115: 130 | C115: 150 | D115: =D114+B115 -> 2409 | E115: =E114+150 -> 3450
A116: 45406 | B116: 110 | C116: 150 | D116: =D115+B116 -> 2519 | E116: =E115+150 -> 3600
A117: 45407 | B117: =35+10+45 -> 90 | C117: 150 | D117: =D116+B117 -> 2609 | E117: =E116+150 -> 3750
A118: 45408 | B118: 50 | C118: 150 | D118: =D117+B118 -> 2659 | E118: =E117+150 -> 3900
A119: 45409 | B119: =20+60+80 -> 160 | C119: 150 | D119: =D118+B119 -> 2819 | E119: =E118+150 -> 4050
A120: 45410 | B120: =20+60+15 -> 95 | C120: 150 | D120: =D119+B120 -> 2914 | E120: =E119+150 -> 4200
A121: 45411 | B121: 80 | C121: 150 | D121: =D120+B121 -> 2994 | E121: =E120+150 -> 4350
A122: 45412 | B122: =40+20+38+45 -> 143 | C122: 150 | D122: =D121+B122 -> 3137 | E122: =E121+150 -> 4500
A123: 45413 | B123: =40+10+200+26+73 -> 349 | C123: 150 | D123: =B123 -> 349 | E123: =C123 -> 150 | G123: Stocks | H123: 2000
A124: 45414 | B124: =40+20+10 -> 70 | C124: 150 | D124: =D123+B124 -> 419 | E124: =C124+C123 -> 300 | G124: SIP | H124: 2300
A125: 45415 | B125: =40+40+10+60 -> 150 | C125: 150 | D125: =D124+B125 -> 569 | E125: =C125+E124 -> 450 | G125: Rent | H125: 8000
A126: 45416 | B126: 30 | C126: 150 | D126: =D125+B126 -> 599 | E126: =E125+150 -> 600 | G126: Expenses | H126: 4650
...

Sheet Sheet2
A1: emo emily
A2: venus afrodita
A3: angryamaon
A4: angelcruz
A5: thepaug
A6: jimenithahot
A7: cietra
A8: mr entertainer
A9: secretsfilmed
A10: nysdel
A11: ellie pink
